{
  "mainAssemblyName": "Presentation",
  "resources": {
    "hash": "sha256-O1Fm0AuEWFEvR6gk1zX5lqJHFiITGB1aitmdSvJXHng=",
    "fingerprinting": {
      "Application.sw96h3c81c.wasm": "Application.wasm",
      "Blazor-ApexCharts.yakf3dc36v.wasm": "Blazor-ApexCharts.wasm",
      "Domain.6f3p61l7pj.wasm": "Domain.wasm",
      "Microsoft.AspNetCore.Components.n4olvahs0z.wasm": "Microsoft.AspNetCore.Components.wasm",
      "Microsoft.AspNetCore.Components.Web.1g7119aggg.wasm": "Microsoft.AspNetCore.Components.Web.wasm",
      "Microsoft.AspNetCore.Components.WebAssembly.qwgyqtwzyo.wasm": "Microsoft.AspNetCore.Components.WebAssembly.wasm",
      "Microsoft.Extensions.Configuration.Abstractions.n3roazub70.wasm": "Microsoft.Extensions.Configuration.Abstractions.wasm",
      "Microsoft.Extensions.Configuration.Json.jgtmx19396.wasm": "Microsoft.Extensions.Configuration.Json.wasm",
      "Microsoft.Extensions.Configuration.7sm4vp77d1.wasm": "Microsoft.Extensions.Configuration.wasm",
      "Microsoft.Extensions.DependencyInjection.Abstractions.mgkge8yzrj.wasm": "Microsoft.Extensions.DependencyInjection.Abstractions.wasm",
      "Microsoft.Extensions.DependencyInjection.g0r86u4i0h.wasm": "Microsoft.Extensions.DependencyInjection.wasm",
      "Microsoft.Extensions.Diagnostics.Abstractions.o97u05c9gb.wasm": "Microsoft.Extensions.Diagnostics.Abstractions.wasm",
      "Microsoft.Extensions.Diagnostics.lk2ttr0x6l.wasm": "Microsoft.Extensions.Diagnostics.wasm",
      "Microsoft.Extensions.Http.0cb6bmw0s9.wasm": "Microsoft.Extensions.Http.wasm",
      "Microsoft.Extensions.Logging.Abstractions.xlg7wzpp8u.wasm": "Microsoft.Extensions.Logging.Abstractions.wasm",
      "Microsoft.Extensions.Logging.y3zk4eoscr.wasm": "Microsoft.Extensions.Logging.wasm",
      "Microsoft.Extensions.Options.gwcojngm5h.wasm": "Microsoft.Extensions.Options.wasm",
      "Microsoft.Extensions.Primitives.4dxofymb0o.wasm": "Microsoft.Extensions.Primitives.wasm",
      "Microsoft.JSInterop.bnwbursv19.wasm": "Microsoft.JSInterop.wasm",
      "Microsoft.JSInterop.WebAssembly.p386u0jty9.wasm": "Microsoft.JSInterop.WebAssembly.wasm",
      "netstandard.16zgcaaij2.wasm": "netstandard.wasm",
      "Presentation.513k3v14cx.wasm": "Presentation.wasm",
      "Riok.Mapperly.Abstractions.v2oa0z4fia.wasm": "Riok.Mapperly.Abstractions.wasm",
      "System.Collections.Concurrent.pzxxji2srh.wasm": "System.Collections.Concurrent.wasm",
      "System.Collections.Immutable.qv69x9lkoy.wasm": "System.Collections.Immutable.wasm",
      "System.Collections.NonGeneric.ud8k4b8ihk.wasm": "System.Collections.NonGeneric.wasm",
      "System.Collections.Specialized.l0yjyij16f.wasm": "System.Collections.Specialized.wasm",
      "System.Collections.ah5vksirtk.wasm": "System.Collections.wasm",
      "System.ComponentModel.Primitives.xh02zg0x4o.wasm": "System.ComponentModel.Primitives.wasm",
      "System.ComponentModel.TypeConverter.4xf36vlbeo.wasm": "System.ComponentModel.TypeConverter.wasm",
      "System.ComponentModel.ek5njsetz3.wasm": "System.ComponentModel.wasm",
      "System.Console.bbl5v80tjr.wasm": "System.Console.wasm",
      "System.Diagnostics.DiagnosticSource.p5l2l2zsdp.wasm": "System.Diagnostics.DiagnosticSource.wasm",
      "System.IO.Pipelines.ij3x2x6ncl.wasm": "System.IO.Pipelines.wasm",
      "System.Linq.Expressions.9iahmzfspu.wasm": "System.Linq.Expressions.wasm",
      "System.Linq.Queryable.wrhrprb5i8.wasm": "System.Linq.Queryable.wasm",
      "System.Linq.iycmryrm1p.wasm": "System.Linq.wasm",
      "System.Memory.g5sf0fdajj.wasm": "System.Memory.wasm",
      "System.Net.Http.Json.7sok06ckw8.wasm": "System.Net.Http.Json.wasm",
      "System.Net.Http.bl8qd6a7ar.wasm": "System.Net.Http.wasm",
      "System.Net.Primitives.qk8k4u090q.wasm": "System.Net.Primitives.wasm",
      "System.ObjectModel.qtptmqpubq.wasm": "System.ObjectModel.wasm",
      "System.Private.CoreLib.56gn4rg17f.wasm": "System.Private.CoreLib.wasm",
      "System.Private.Uri.keib3tshnh.wasm": "System.Private.Uri.wasm",
      "System.Runtime.InteropServices.JavaScript.4wymnd9fjf.wasm": "System.Runtime.InteropServices.JavaScript.wasm",
      "System.Runtime.InteropServices.pt770ios6x.wasm": "System.Runtime.InteropServices.wasm",
      "System.Runtime.Serialization.Primitives.xrflky9lfu.wasm": "System.Runtime.Serialization.Primitives.wasm",
      "System.Runtime.mmk0t79iqh.wasm": "System.Runtime.wasm",
      "System.Text.Encodings.Web.j8jbnca1on.wasm": "System.Text.Encodings.Web.wasm",
      "System.Text.Json.7g5i952usu.wasm": "System.Text.Json.wasm",
      "System.Text.RegularExpressions.3zydt3n8n9.wasm": "System.Text.RegularExpressions.wasm",
      "System.Threading.s3qkemyun8.wasm": "System.Threading.wasm",
      "System.cunp5qiwjj.wasm": "System.wasm",
      "dotnet.native.ffj4va6u6z.js": "dotnet.native.js",
      "dotnet.native.2hyxkv42ig.wasm": "dotnet.native.wasm",
      "dotnet.js": "dotnet.js",
      "dotnet.runtime.d1pzlaz2ez.js": "dotnet.runtime.js",
      "icudt_CJK.tjcz0u77k5.dat": "icudt_CJK.dat",
      "icudt_EFIGS.tptq2av103.dat": "icudt_EFIGS.dat",
      "icudt_no_CJK.lfu7j35m59.dat": "icudt_no_CJK.dat"
    },
    "jsModuleNative": {
      "dotnet.native.ffj4va6u6z.js": "sha256-pf2P11GPrPDRMygks46BPb4T9E0RA0y6N7Sb3NBSRvg="
    },
    "jsModuleRuntime": {
      "dotnet.runtime.d1pzlaz2ez.js": "sha256-gbZjXNFbH7V8lcix+H0TUDJHLeFUA3n3IMu7fLh4D80="
    },
    "wasmNative": {
      "dotnet.native.2hyxkv42ig.wasm": "sha256-xlytwbxmiDUTywiVKc1sLcefPYKqy9O+jtgGYuxLDu0="
    },
    "icu": {
      "icudt_CJK.tjcz0u77k5.dat": "sha256-SZLtQnRc0JkwqHab0VUVP7T3uBPSeYzxzDnpxPpUnHk=",
      "icudt_EFIGS.tptq2av103.dat": "sha256-8fItetYY8kQ0ww6oxwTLiT3oXlBwHKumbeP2pRF4yTc=",
      "icudt_no_CJK.lfu7j35m59.dat": "sha256-L7sV7NEYP37/Qr2FPCePo5cJqRgTXRwGHuwF5Q+0Nfs="
    },
    "coreAssembly": {
      "System.Private.CoreLib.56gn4rg17f.wasm": "sha256-Yz73c00IHqv2Sec8zHb9EDiHoIp0Xs0c6enaU1XB/0g=",
      "System.Runtime.InteropServices.JavaScript.4wymnd9fjf.wasm": "sha256-3IoLyXDPZlSSNuf0cCFYH/6pnHsiIz+bg/ptKuGnMiI="
    },
    "assembly": {
      "Application.sw96h3c81c.wasm": "sha256-rNQ/PGjrZP0d9cI8baPxBn7C94ZGMIJX7eJJrjchw0I=",
      "Blazor-ApexCharts.yakf3dc36v.wasm": "sha256-isvT81kzaKoBIvhUgBp+x2RfkrlVZbUpfYVUyMtpTzk=",
      "Domain.6f3p61l7pj.wasm": "sha256-bqjUm2QSHSaDE9hsgHthZmHUIn9ebTdxdxtQJRqCoFU=",
      "Microsoft.AspNetCore.Components.n4olvahs0z.wasm": "sha256-Z2S/aUV+FIwnBReV5EGhF9FSnnkuSDOVI/eVUQlJeHw=",
      "Microsoft.AspNetCore.Components.Web.1g7119aggg.wasm": "sha256-Dx/b3kub5i+qQgnzHE2Pcg+BGzccoNeNBbQZF1iTH0Q=",
      "Microsoft.AspNetCore.Components.WebAssembly.qwgyqtwzyo.wasm": "sha256-GjgORQschepw/Fj0uPtkGte5ppoyG7DlGcdsMN/T6eA=",
      "Microsoft.Extensions.Configuration.Abstractions.n3roazub70.wasm": "sha256-M/V9DIZ9otM7/qEt+xn3wagkoRiLOf4JMPyDoo6WUM8=",
      "Microsoft.Extensions.Configuration.Json.jgtmx19396.wasm": "sha256-XQykit2HYxnB0emmOc5bra6XuZq3KgCfazi8kFAErDs=",
      "Microsoft.Extensions.Configuration.7sm4vp77d1.wasm": "sha256-V/8lrAHQfJYsJtV+bKRHL6fmMFhJhAOyoTNfGTbwTdQ=",
      "Microsoft.Extensions.DependencyInjection.Abstractions.mgkge8yzrj.wasm": "sha256-ambu+DD9SP3J4BkXqnz/LuR30vMyNcUFg19XzzkxZwc=",
      "Microsoft.Extensions.DependencyInjection.g0r86u4i0h.wasm": "sha256-wPj/fOeoE7JKOgIYh6OIvl/k3Iw6EPDmmXDjtnQ6rJk=",
      "Microsoft.Extensions.Diagnostics.Abstractions.o97u05c9gb.wasm": "sha256-tEtUKTeItXncbYJzaOn0W/BY6wHDdtVCzr0FPuKmN4M=",
      "Microsoft.Extensions.Diagnostics.lk2ttr0x6l.wasm": "sha256-u4RUZ6A9cWnQlgCP/S7IxI1Wh8+1iQrhwgBkYE0TEWo=",
      "Microsoft.Extensions.Http.0cb6bmw0s9.wasm": "sha256-IH4lqbeS41PGvIav12yDevpwq7Xg91SWb1WWHYOEXVU=",
      "Microsoft.Extensions.Logging.Abstractions.xlg7wzpp8u.wasm": "sha256-K1TVDGxuyo+acVQvCecj7FtMDG3FWyEnwUFr3zTnBV4=",
      "Microsoft.Extensions.Logging.y3zk4eoscr.wasm": "sha256-QhWV6R3UsAbvd90hOpKEo7wmHVsEGWtliqDxgSwvMrw=",
      "Microsoft.Extensions.Options.gwcojngm5h.wasm": "sha256-UIbQSVx6SN1qBPZTZyeZAoTd3ZiY7RvlOEGUMT+0RL0=",
      "Microsoft.Extensions.Primitives.4dxofymb0o.wasm": "sha256-GOr7jc/eCieZrQYoXRn79eLSsesIfFB55wQZIVTSNIY=",
      "Microsoft.JSInterop.bnwbursv19.wasm": "sha256-ByRdcTZBu9FmUutsF3pnt7+mo07JiDGb2mBrnNn4H5Y=",
      "Microsoft.JSInterop.WebAssembly.p386u0jty9.wasm": "sha256-hbzWuXrlepIqY/y+nQ2ZAFer2/njy1dc+Y4LUaAaL5E=",
      "netstandard.16zgcaaij2.wasm": "sha256-99UzSprhAIS5OWuUI6X99DPJFuGJ+u7sv2qXMH5Mbxc=",
      "Presentation.513k3v14cx.wasm": "sha256-WRu9kSNcXWVQdld8SsG22KE008ogAytkAu/ur3Sq2qg=",
      "Riok.Mapperly.Abstractions.v2oa0z4fia.wasm": "sha256-ZwToh0+onnsuEEi4ISoq7tGM9S9l8NmpDtywTW7VASI=",
      "System.Collections.Concurrent.pzxxji2srh.wasm": "sha256-VcU64vh2YLE1IgmOJyvmyH4xSgG9ICznM3C1z+xfEAw=",
      "System.Collections.Immutable.qv69x9lkoy.wasm": "sha256-FmAtnWkr+XJNdmArpb5I1c33W7Tp7ehWnnq2OenIbEI=",
      "System.Collections.NonGeneric.ud8k4b8ihk.wasm": "sha256-jghclVhUYQHD/mDiZ1EZFHXP+ID76HT/gtlgfEtQ5pk=",
      "System.Collections.Specialized.l0yjyij16f.wasm": "sha256-9Yyj3DBjCP8xoNCavuY/sH95BtM6x4NCfJ2Yw01A6fQ=",
      "System.Collections.ah5vksirtk.wasm": "sha256-gm6CMot0SAGSVu390zY9XH2xe00hD0veWcMPjNtXy70=",
      "System.ComponentModel.Primitives.xh02zg0x4o.wasm": "sha256-+w3ZVtptoo+8tSakaAv08abP5sRa+3t44/bU5HHFo+M=",
      "System.ComponentModel.TypeConverter.4xf36vlbeo.wasm": "sha256-WCW9CZbgzgRp28zV5y4C2kpt6Mq2wesB3wAWR9KKEnY=",
      "System.ComponentModel.ek5njsetz3.wasm": "sha256-7n7ghIpXsa9b0B2ogCKFeKszbubZfTop3s6xAVOqZ9I=",
      "System.Console.bbl5v80tjr.wasm": "sha256-2SXgDbjkdQHBdbJPPJs1lxMqjsjg9N7Qh3/d6cZeX7o=",
      "System.Diagnostics.DiagnosticSource.p5l2l2zsdp.wasm": "sha256-Y3v/w3nwej6CneL12fRO/CI4ouNyJPcfBSEZpWZeEZk=",
      "System.IO.Pipelines.ij3x2x6ncl.wasm": "sha256-0uljQYkN7r22Bww1ENZAVGTupoPwfKICKYE7IbIfkLU=",
      "System.Linq.Expressions.9iahmzfspu.wasm": "sha256-j34pTS3/c0ifGzBtqx5+GRSuioXsZEc2F3AewkuvKvk=",
      "System.Linq.Queryable.wrhrprb5i8.wasm": "sha256-vIfCVy17YZ9avOSiTou27zW/arurAL9SScxNnb2nAAY=",
      "System.Linq.iycmryrm1p.wasm": "sha256-Gt4igCehQIpA/Og3cLsyQjq0GbSzCOMZ97pPWdo3M+g=",
      "System.Memory.g5sf0fdajj.wasm": "sha256-vNeDdoRRdSiX7LqJuHZZuiImIjaK18jzznPDNCrspfo=",
      "System.Net.Http.Json.7sok06ckw8.wasm": "sha256-ia1v1t0232OdLQk3UqwornIiHjt67uZlyE81Rvs7RUU=",
      "System.Net.Http.bl8qd6a7ar.wasm": "sha256-/xIA5/vD+w4OisB1Nw1Pern0+rZxys2HFRYvdTD8DwM=",
      "System.Net.Primitives.qk8k4u090q.wasm": "sha256-lpuToxoC6gyjBIE2Z0NrXP7Q+Zku/Hml1ND72k+jG48=",
      "System.ObjectModel.qtptmqpubq.wasm": "sha256-/rXUzqlHPqEhnzNyisIb9kesOINuRJooQRfQ77EBIuI=",
      "System.Private.Uri.keib3tshnh.wasm": "sha256-FFeTHvYd9kPkaul+UCsCg1gJnGN+B4URm06nHW8KHu8=",
      "System.Runtime.InteropServices.pt770ios6x.wasm": "sha256-o9TYS1cOs+zSxdLbZRl/3dOSXBTUkZ+VGv4sJ86qi/U=",
      "System.Runtime.Serialization.Primitives.xrflky9lfu.wasm": "sha256-45BsPGG9k1KE+c9+TADErTMPOK4F2rFNpikJXDRw/L8=",
      "System.Runtime.mmk0t79iqh.wasm": "sha256-ks4nF7HmFebUl/c5tTcMSahseA5esLbgtHsWgmYf7Z4=",
      "System.Text.Encodings.Web.j8jbnca1on.wasm": "sha256-3cJRUrFjSoiaGlI3OmHNndawtN8Y5lEgLHYI76jlAvo=",
      "System.Text.Json.7g5i952usu.wasm": "sha256-F2kmNO2OMk5r5M40tJFUvZ1qv06gEllbkPD0D19TxSA=",
      "System.Text.RegularExpressions.3zydt3n8n9.wasm": "sha256-sXTH9c57ccmOHrE+Bpsiewg0xWGtHrbl8KBKpTJW9VA=",
      "System.Threading.s3qkemyun8.wasm": "sha256-2LiNsHhr+Hy1ERngk7sVqZsCTw6tQpFMHmgxkuxOKpo=",
      "System.cunp5qiwjj.wasm": "sha256-DM5iEENhrifGKn33Y7cqRzxC0OtHXYOKO13icwIazj8="
    }
  },
  "cacheBootResources": true,
  "debugLevel": 0,
  "linkerEnabled": true,
  "globalizationMode": "sharded",
  "extensions": {
    "blazor": {}
  }
}